{
  "prid": "2234987",
  "ministry": "Ministry of Defence",
  "title": "MoD inks Rs 5,083 crore contracts for ALH Mk-II (MR) & VL-Shtil missiles",
  "posted_on_raw": "03 MAR 2026 3:22PM",
  "source_url": "https://www.pib.gov.in/PressReleasePage.aspx?PRID=2234987",
  "pdfs": [],
  "text": "Press Release:Press Information Bureau\n\nMinistry of Defence\n\nMoD inks Rs 5,083 crore contracts for ALH Mk-II (MR) & VL-Shtil missiles\n\nPosted On:\n03 MAR 2026 3:22PM by PIB Delhi\n\nMinistry of Defence, on March 03, 2026, signed contracts worth a total of Rs 5,083 crore for the acquisition of six Advanced Light Helicopters (ALH) Mk-II (Maritime Role) for the Indian Coast Guard and Surface-to-Air Vertical Launch - Shtil missiles for the Indian Navy. The contracts were inked in the presence of Defence Secretary Shri Rajesh Kumar Singh at South Block, New Delhi.\n\n\n\nALH Mk-III (MR)\n\nThe contract for ALH Mk-III (MR) along with operational role equipment, an engineering support package, and performance-based logistics support, valued at Rs 2,901 crore, has been inked with Hindustan Aeronautics Limited, Bengaluru under the Buy (Indian-Indigenously Designed Developed and Manufactured) category.\n\n\n\n\n\nThese twin-engine helicopters incorporate state-of-the-art features superior to the currently operated airborne platforms and are capable of undertaking a wide spectrum of maritime security missions from shore-based airfields as well as from ships at sea. The induction will significantly enhance the Indian Coast Guard’s capability for fulfilling the duties of safety and protection of artificial islands, offshore installations, and protection of fishermen & marine environment.\n\nThe project envisages supply of equipment from more than 200 MSMEs and is expected to generate approximately 65 lakh man-hours of employment. The contract reinforces the Government’s commitment to\nAatmanirbhar Bharat\nand the\nMake-in-India\ninitiative, while further strengthening the nation’s maritime security architecture.\n\nVertical Launch - Shtil missiles\n\nThe contract for the procurement of Surface-to-Air Vertical Launch - Shtil missiles and associated missile holding frames, valued at Rs 2,182 crore, has been signed with JSC Rosoboronexport, Russian Federation. The acquisition is intended to substantially enhance the air defence capabilities of frontline warships against a wide spectrum of aerial threats.\n\n\n\nThe system will reinforce the layered air defence architecture onboard the platforms of the Indian Navy by providing rapid-reaction, all-weather engagement capability and improved survivability in contested maritime environments. The contract further underscores the longstanding and time-tested defence partnership between India and Russia, founded on mutual trust and strategic alignment.\n\n*******\n\nVK/Savvy\n\n(Release ID: 2234987)\n\nVisitor Counter : 446\n\nMinistry of Defence\n\nMoD inks Rs 5,083 crore contracts for ALH Mk-II (MR) & VL-Shtil missiles\n\nPosted On:\n03 MAR 2026 3:22PM by PIB Delhi\n\nMinistry of Defence, on March 03, 2026, signed contracts worth a total of Rs 5,083 crore for the acquisition of six Advanced Light Helicopters (ALH) Mk-II (Maritime Role) for the Indian Coast Guard and Surface-to-Air Vertical Launch - Shtil missiles for the Indian Navy. The contracts were inked in the presence of Defence Secretary Shri Rajesh Kumar Singh at South Block, New Delhi.\n\n\n\nALH Mk-III (MR)\n\nThe contract for ALH Mk-III (MR) along with operational role equipment, an engineering support package, and performance-based logistics support, valued at Rs 2,901 crore, has been inked with Hindustan Aeronautics Limited, Bengaluru under the Buy (Indian-Indigenously Designed Developed and Manufactured) category.\n\n\n\n\n\nThese twin-engine helicopters incorporate state-of-the-art features superior to the currently operated airborne platforms and are capable of undertaking a wide spectrum of maritime security missions from shore-based airfields as well as from ships at sea. The induction will significantly enhance the Indian Coast Guard’s capability for fulfilling the duties of safety and protection of artificial islands, offshore installations, and protection of fishermen & marine environment.\n\nThe project envisages supply of equipment from more than 200 MSMEs and is expected to generate approximately 65 lakh man-hours of employment. The contract reinforces the Government’s commitment to\nAatmanirbhar Bharat\nand the\nMake-in-India\ninitiative, while further strengthening the nation’s maritime security architecture.\n\nVertical Launch - Shtil missiles\n\nThe contract for the procurement of Surface-to-Air Vertical Launch - Shtil missiles and associated missile holding frames, valued at Rs 2,182 crore, has been signed with JSC Rosoboronexport, Russian Federation. The acquisition is intended to substantially enhance the air defence capabilities of frontline warships against a wide spectrum of aerial threats.\n\n\n\nThe system will reinforce the layered air defence architecture onboard the platforms of the Indian Navy by providing rapid-reaction, all-weather engagement capability and improved survivability in contested maritime environments. The contract further underscores the longstanding and time-tested defence partnership between India and Russia, founded on mutual trust and strategic alignment.\n\n*******\n\nVK/Savvy\n\n(Release ID: 2234987)",
  "fetched_at_utc": "2026-03-03T10:50:43.827037+00:00"
}