{
  "prid": "2238343",
  "ministry": "Ministry of Science & Technology",
  "title": "PARLIAMENT QUESTION: HIGH-IMPACT RESEARCH AREAS",
  "posted_on_raw": "11 MAR 2026 5:18PM",
  "source_url": "https://www.pib.gov.in/PressReleasePage.aspx?PRID=2238343",
  "pdfs": [],
  "text": "Press Release:Press Information Bureau\n\nMinistry of Science & Technology\n\nPARLIAMENT QUESTION: HIGH-IMPACT RESEARCH AREAS\n\nPosted On:\n11 MAR 2026 5:18PM by PIB Delhi\n\nPrime Minister Shri Narendra Modi chaired the first meeting of the Governing Board of Anusandhan National Research Foundation (ANRF) on 10\nth\n September, 2024. The meeting focussed on discussion about India’s Science and Technology landscape and redesigning of research and development programmes. The board discussed several areas of strategic interventions of ANRF which include India’s international status in important sectors, aligning R&D with national priorities, promoting inclusive growth, capacity building, driving scientific advances and innovation ecosystem, as well as bridging the gap between academic research and industrial applications. The major programs initiated by ANRF since its inceptions are given below:-\n\nMission for Advancement in High-impact Areas (MAHA) program of ANRF addresses priority-driven, solution-focused research in mission-mode that would catalyse multi-institutional, multi-disciplinary and multi-investigator collaboration to address scientific challenges and advance the frontiers of technology in key scientific areas. So far, ANRF has identified and launched Electric Vehicle (EV) Mission, 2D Innovation Hub, MedTech Mission, AI for Science and Engineering and CRM Research Program as the priority areas of focus under MAHA program.\n\nSeveral broad-based programs like Advanced Research Grant (ARG), Prime Minister Early Career Research Grant (PMECRG), Inclusivity Research Grant (IRG) launched by ANRF to providing financial assistance to researchers and scientists in academic institutions in order to create supportive environment for doing research in frontier areas of science and engineering all across the country.\n\nConvergence Research Centres of Excellence (CoE) to establish \"convergence\" research Centres of Excellence (CoEs) launched by ANRF to undertake cutting edge, innovative and impactful research at the interface of Science, Technology, Humanities, Social Sciences and Society. These Centres will address complex societal challenges that require integrated perspectives from both technical and social sciences/humanities domains.\n\nANRF launched Centre of Excellence for Science, Technology and Innovation Indicators and Analytics (COE-STIIA) with the aim to strengthen the institutional mechanism for STI indicators with an end-to-end system. The key objective is to enhance the quality, contextual relevance and applicability of India’s STI indicators, their analysis, interpretations and dissemination of information and insights at various levels of policy and program planning, as well as foster alignment with the global indicator frameworks to position India effectively in international indices.\n\nANRF launched PAIR (Partnerships for Accelerated Innovation and Research) program which is designed to boost the research capability of those institutions including State Universities where research is at a nascent stage but which have the potential to perform well, in a mentorship mode by pairing them with well-established top-tier research institutions in a hub and spoke framework.\n\nThe ANRF Translational Research and Innovation (ATRI) initiative will bring together all key stakeholders to channelise the expertise and resources for unlocking the tremendous innovation potential. Under this initiative, ANRF will establish ATRI centres to provide targeted support for advancing potential technologies from TRL 4 to TRL 7, thereby strengthening the innovation pipeline from lab to market.\n\nANRF has launched National Post-Doctoral Fellowship (NPDF) program to support young researchers after finishing Ph.D. which is effective to retain them in the country. ANRF launched Ramanujan Fellowship to attract brilliant scientists and engineers of Indian origin working abroad to return and take up scientific research positions in India.\n\nThe ANRF has launched programs such as the National Science Chair, JC Bose Grant and Prime Minister Professorship programs to recognise eminent senior scientists for their outstanding contributions at both national and international levels. These initiatives also aim to leverage the expertise of scientists and faculty from reputed academic institutions, research laboratories and industry.\n\nThe details of the grants awarded in high-impact areas are given below:\n\nSr. No.\n\nProject Title\n\nInstitute Name\n\nTotal Cost\n\n(₹ in Crore)\n\n1\n\nDevelopment and Demonstration of Materials and Fabrication Technologies for Tropical Batteries\n\nInternational Advanced Research Centre For Powder Metallurgy And New Materials (Arci), Hyderabad\n\n68.38\n\n2\n\nTe-MobiX: Safe and Degradation-controlled Batteries with Efficient Charging for Tropical e-Mobility Excellence\n\nIndian Institute Of Technology (Banaras Hindu University), Varanasi\n\n47.77\n\n3\n\nGrid Readiness for EV: Enablers and Technological developments (GREET)\n\nIndian Institute Of Technology Kanpur\n\n47.45\n\n4\n\nEmpowering Research in Indigenous Development of EV Sub-systems (E-RIDES)\n\nIndian Institute Of Technology Bombay\n\n56.56\n\n5\n\nDevelopment of high-power Grid-friendly Conductive and Static Wireless Chargers for Electric Vehicles\n\nIndian Institute Of Technology Kharagpur\n\n18.37\n\n6\n\nRare Earth Magnet-Free Axial Flux Synchronous, Radial Flux Switched Reluctance Motor and their Controllers for EV Applications\n\nNational Institute Of Technology Karnataka, Surathkal\n\n7.76\n\n7\n\nDevelopment of wide-bandgap semiconductors based highly efficient power electronics systems for Electric Vehicle\n\nCsir-Central Electronics Engineering Research Institute(Csir-Ceeri), Pilani\n\n18.41\n\nThe Department has launched several mission-mode initiatives to strengthen the innovation ecosystem and promote high-impact research in emerging technology areas. The National Quantum Mission (NQM), approved by the Union Cabinet with an outlay of ₹6003.65 crore for a period of eight years, aims to support research and development in quantum computing, quantum communication, quantum sensing and quantum materials.\n\nUnder the Mission, four Thematic Hubs have been established in September 2024: Quantum Computing at the Indian Institute of Science (IISc), Bengaluru; Quantum Communication at the Indian Institute of Technology (IIT) Madras in association with C-DOT; Quantum Sensing & Metrology at IIT Bombay; and Quantum Materials & Devices at IIT Delhi. These Hubs are undertaking activities in technology development, human resource development, entrepreneurship development and industry collaboration, as well as international collaborations, to strengthen the quantum innovation ecosystem in the country.\n\nThe National Mission on Interdisciplinary Cyber-Physical Systems (NM-ICPS) supports the development of Cyber-Physical Systems technologies through a network of Technology Innovation Hubs (TIHs) across academic institutions, focusing on areas such as AI, robotics, autonomous systems, smart manufacturing and advanced communication technologies.\n\nIn addition, the Anusandhan National Research Foundation (ANRF) has initiated several mission-mode programmes, including Drones, Water, 6G and Leapfrog Demonstrators, to promote solution-oriented and translational research in priority technology areas.Bottom of Form\n\nThis information was given by the\nMinister of State (Independent charge) for the Ministry of Science and Technology & Earth Sciences Dr. Jitendra Singh\nin a written reply in the Lok Sabha today.\n\n*****\n\nNKR/FK/AK/NM\n\n(Release ID: 2238343)\n\nVisitor Counter : 52\n\nRead this release in:\n\nहिन्दी\n\nMinistry of Science & Technology\n\nPARLIAMENT QUESTION: HIGH-IMPACT RESEARCH AREAS\n\nPosted On:\n11 MAR 2026 5:18PM by PIB Delhi\n\nPrime Minister Shri Narendra Modi chaired the first meeting of the Governing Board of Anusandhan National Research Foundation (ANRF) on 10\nth\n September, 2024. The meeting focussed on discussion about India’s Science and Technology landscape and redesigning of research and development programmes. The board discussed several areas of strategic interventions of ANRF which include India’s international status in important sectors, aligning R&D with national priorities, promoting inclusive growth, capacity building, driving scientific advances and innovation ecosystem, as well as bridging the gap between academic research and industrial applications. The major programs initiated by ANRF since its inceptions are given below:-\n\nMission for Advancement in High-impact Areas (MAHA) program of ANRF addresses priority-driven, solution-focused research in mission-mode that would catalyse multi-institutional, multi-disciplinary and multi-investigator collaboration to address scientific challenges and advance the frontiers of technology in key scientific areas. So far, ANRF has identified and launched Electric Vehicle (EV) Mission, 2D Innovation Hub, MedTech Mission, AI for Science and Engineering and CRM Research Program as the priority areas of focus under MAHA program.\n\nSeveral broad-based programs like Advanced Research Grant (ARG), Prime Minister Early Career Research Grant (PMECRG), Inclusivity Research Grant (IRG) launched by ANRF to providing financial assistance to researchers and scientists in academic institutions in order to create supportive environment for doing research in frontier areas of science and engineering all across the country.\n\nConvergence Research Centres of Excellence (CoE) to establish \"convergence\" research Centres of Excellence (CoEs) launched by ANRF to undertake cutting edge, innovative and impactful research at the interface of Science, Technology, Humanities, Social Sciences and Society. These Centres will address complex societal challenges that require integrated perspectives from both technical and social sciences/humanities domains.\n\nANRF launched Centre of Excellence for Science, Technology and Innovation Indicators and Analytics (COE-STIIA) with the aim to strengthen the institutional mechanism for STI indicators with an end-to-end system. The key objective is to enhance the quality, contextual relevance and applicability of India’s STI indicators, their analysis, interpretations and dissemination of information and insights at various levels of policy and program planning, as well as foster alignment with the global indicator frameworks to position India effectively in international indices.\n\nANRF launched PAIR (Partnerships for Accelerated Innovation and Research) program which is designed to boost the research capability of those institutions including State Universities where research is at a nascent stage but which have the potential to perform well, in a mentorship mode by pairing them with well-established top-tier research institutions in a hub and spoke framework.\n\nThe ANRF Translational Research and Innovation (ATRI) initiative will bring together all key stakeholders to channelise the expertise and resources for unlocking the tremendous innovation potential. Under this initiative, ANRF will establish ATRI centres to provide targeted support for advancing potential technologies from TRL 4 to TRL 7, thereby strengthening the innovation pipeline from lab to market.\n\nANRF has launched National Post-Doctoral Fellowship (NPDF) program to support young researchers after finishing Ph.D. which is effective to retain them in the country. ANRF launched Ramanujan Fellowship to attract brilliant scientists and engineers of Indian origin working abroad to return and take up scientific research positions in India.\n\nThe ANRF has launched programs such as the National Science Chair, JC Bose Grant and Prime Minister Professorship programs to recognise eminent senior scientists for their outstanding contributions at both national and international levels. These initiatives also aim to leverage the expertise of scientists and faculty from reputed academic institutions, research laboratories and industry.\n\nThe details of the grants awarded in high-impact areas are given below:\n\nSr. No.\n\nProject Title\n\nInstitute Name\n\nTotal Cost\n\n(₹ in Crore)\n\n1\n\nDevelopment and Demonstration of Materials and Fabrication Technologies for Tropical Batteries\n\nInternational Advanced Research Centre For Powder Metallurgy And New Materials (Arci), Hyderabad\n\n68.38\n\n2\n\nTe-MobiX: Safe and Degradation-controlled Batteries with Efficient Charging for Tropical e-Mobility Excellence\n\nIndian Institute Of Technology (Banaras Hindu University), Varanasi\n\n47.77\n\n3\n\nGrid Readiness for EV: Enablers and Technological developments (GREET)\n\nIndian Institute Of Technology Kanpur\n\n47.45\n\n4\n\nEmpowering Research in Indigenous Development of EV Sub-systems (E-RIDES)\n\nIndian Institute Of Technology Bombay\n\n56.56\n\n5\n\nDevelopment of high-power Grid-friendly Conductive and Static Wireless Chargers for Electric Vehicles\n\nIndian Institute Of Technology Kharagpur\n\n18.37\n\n6\n\nRare Earth Magnet-Free Axial Flux Synchronous, Radial Flux Switched Reluctance Motor and their Controllers for EV Applications\n\nNational Institute Of Technology Karnataka, Surathkal\n\n7.76\n\n7\n\nDevelopment of wide-bandgap semiconductors based highly efficient power electronics systems for Electric Vehicle\n\nCsir-Central Electronics Engineering Research Institute(Csir-Ceeri), Pilani\n\n18.41\n\nThe Department has launched several mission-mode initiatives to strengthen the innovation ecosystem and promote high-impact research in emerging technology areas. The National Quantum Mission (NQM), approved by the Union Cabinet with an outlay of ₹6003.65 crore for a period of eight years, aims to support research and development in quantum computing, quantum communication, quantum sensing and quantum materials.\n\nUnder the Mission, four Thematic Hubs have been established in September 2024: Quantum Computing at the Indian Institute of Science (IISc), Bengaluru; Quantum Communication at the Indian Institute of Technology (IIT) Madras in association with C-DOT; Quantum Sensing & Metrology at IIT Bombay; and Quantum Materials & Devices at IIT Delhi. These Hubs are undertaking activities in technology development, human resource development, entrepreneurship development and industry collaboration, as well as international collaborations, to strengthen the quantum innovation ecosystem in the country.\n\nThe National Mission on Interdisciplinary Cyber-Physical Systems (NM-ICPS) supports the development of Cyber-Physical Systems technologies through a network of Technology Innovation Hubs (TIHs) across academic institutions, focusing on areas such as AI, robotics, autonomous systems, smart manufacturing and advanced communication technologies.\n\nIn addition, the Anusandhan National Research Foundation (ANRF) has initiated several mission-mode programmes, including Drones, Water, 6G and Leapfrog Demonstrators, to promote solution-oriented and translational research in priority technology areas.Bottom of Form\n\nThis information was given by the\nMinister of State (Independent charge) for the Ministry of Science and Technology & Earth Sciences Dr. Jitendra Singh\nin a written reply in the Lok Sabha today.\n\n*****\n\nNKR/FK/AK/NM\n\n(Release ID: 2238343)",
  "fetched_at_utc": "2026-03-11T14:57:13.064446+00:00"
}