{
  "prid": "2247814",
  "ministry": "Ministry of Electronics & IT",
  "title": "Government's Semicon India Programme to develop a complete ecosystem ranging from design to manufacturing",
  "posted_on_raw": "01 APR 2026 4:59PM",
  "source_url": "https://www.pib.gov.in/PressReleasePage.aspx?PRID=2247814",
  "pdfs": [],
  "text": "Press Release Page | Press Information Bureau\n\nMinistry of Electronics & IT\n\nGovernment's Semicon India Programme to develop a complete ecosystem ranging from design to manufacturing\n\nGovernment has approved 10 projects with investment commitments of about ₹1.6 lakh crore\nCommercial production from two plants has commenced; 2 more plants to start commercial production this year\n\nPosted On:\n01 APR 2026 4:59PM by PIB Delhi\n\nIndia’s electronic manufacturing strategy is driven by the Prime Minister’s vision of AtmaNirbhar Bharat and Making India a global manufacturing hub. The Government adopted a structured and targeted policy for electronics manufacturing across the entire value chain including semiconductors.\n\nAs a result of these policies, electronics manufacturing in India has expanded significantly in the last 11 years. It can be seen from the following statistics:\n\n\n\n#\n\n2014-15\n\n2024-25\n\nRemarks\n\nProduction of electronics goods (₹)\n\n~1.9 Lakh Cr\n\n~12 Lakh Cr\n\nIncreased 6 times\n\nExport of electronics goods (₹)\n\n38 thousand Cr\n\n~3.3 Lakh Cr\n\nIncreased 8 times\n\nProduction of mobile phones (₹)\n\n18 thousand Cr\n\n5.45 Lakh Cr\n\nIncreased 28 times\n\nExport of mobile phones (₹)\n\n1,500 Cr.\n\n2 Lakh Cr\n\nIncreased 127 times\n\nMobile Phone imported (units)\n\n75% of the total demand\n\n0.02% of the total demand\n\n\n\n\n\n\n\nSemicon India Programme\n\nSemiconductors is a foundational and strategic industry. Semiconductors are used in almost every device.\n\n\n\nTo promote the development of its manufacturing ecosystem in India, the Government launched Semicon India Programme in January 2022. It aims at developing a complete ecosystem, ranging from design, fabrication, assembly, testing, packaging and module manufacturing.\n\n\n\nIn a short span of four years, the Government has approved 10 projects with investment commitments of about ₹1.6 lakh crore. Commercial production from two plants (Micron and Kaynes) has commenced with 2 more plants to start commercial production this year.\n\n\n\nThe details of the approved Semiconductor manufacturing units are placed at\n Annexure I.\n\n\n\nDeveloping India’s chip design ecosystem:\n\nGovernment is developing India’s chip design ecosystem in two ways:\n\n\n\n1.\nSupporting Indian design engineers through chip design tools\n\nIn a one of its kind initiative in the world, Government has provided cutting edge chip design tools from 8 different companies to 315 universities at no cost. So far, their usage has exceeded 200 lakh hours.\n\n\n\nUsing these tools 211, chips have been taped out by 75 institutions across India including 149 chips at 180nm, SCL Mohali and 62 chip at overseas foundries.\n\n\n\n2.\nSupporting Indian design companies through grant, free design tool and fabrication support:\n\nGovernment has approved 24 projects for the design of semiconductor chips and SoCs. These projects address critical sectors such as video surveillance, drone detection, energy metering, microprocessors, satellite communications, and broadband and IoT SoCs.\n\n\n\nOut of 24 projects, 14 companies have raised venture capital funding of more than Rs 650 Cr to scale up and productize their solutions. Seven (7) chips have been successfully fabricated at various nodes including advanced nodes such as 12 nm.\n\n\n\nFurther, to enhance bilateral collaboration on opportunities to advance resilient semiconductor supply chains and leverage complementary strengths, the Government has entered into MoU with United States, Japan, European Union, Singapore and Netherlands.\n\n\n\nEmployment generation\n\nThe growth of the electronics manufacturing sector has led to substantial employment generation. As per industry estimates, it supports around 25 lakh jobs, including direct and indirect employment.\n\nOut of this, the mobile phone manufacturing sector alone supports around 12 lakh jobs, across manufacturing, logistics, supply chains and allied services.\n\n\n\nApart from this, the Government is implementing flagship schemes to further boost employment by attracting investments.\n\n\n\nUnder the India Semiconductor Mission (ISM), 10 semiconductor units are under construction. As a foundational industry, semiconductor manufacturing is expected to have a cascading impact on employment generation across the supply chain and allied sectors, leading to significant indirect job creation.\n\nSimilarly, under Electronics Component Manufacturing Scheme (ECMS), 249 applications have been received for components, base materials and capital equipments such as PCBs, capacitors, laminates etc.\n\n\n\nIndia Semiconductor Mission 2.0:\nBuilding on the success of Semicon India Programme and further enhance the capabilities in semiconductors, FM, in the Union Budget 2026-27, announced India Semiconductor Mission 2.0 for manufacture of equipment and materials, design full stack, Indian IP and fortify supply chains.\n\n\n\n****\n\n\n\nAnnexure-I\n\nDetails of approved semiconductor manufacturing projects:\n\n\n\n1.\nMicron Technology Inc.\nis establishing semiconductor manufacturing facility in Gujarat with an investment of Rs.22,516 crore. Micron’s facility in India will enable assembly and test manufacturing for both DRAM and NAND products and address demand from domestic and international markets. The production capacity is around 14 million units per week.\n\n2.\nTata Electronics Private Limited (TEPL)\nis establishing semiconductor manufacturing facility in Gujarat with an investment of Rs. 91,526 crore. The fab facility will be set up in technology partnership with PSMC, Taiwan. The production capacity of the project would be around 50,000 wafer starts per month (WSPM).\n\n3.\nTata Electronics Private Limited (TEPL)\nis establishing semiconductor manufacturing facility in Assam with an investment of Rs.27,120 crores. The facility will use indigenous semiconductor packaging technologies with a production capacity of 48 million units per day.\n\n4.\nCG Power and Industrial Solutions Limited\nis establishing semiconductor manufacturing facility in Gujarat with an investment of Rs. 7,584 crore. The facility will be set up as a joint venture partnership with Renesas Electronics America Inc., USA, and STARS Microelectronic, Thailand. The Technology would be provided for this facility by Renesas Electronics Corporation, Japan and STARS Microelectronic, Thailand. The production capacity would be around 15.07 million units per day.\n\n5.\nKaynes Technology India Limited (KTIL)\nis establishing semiconductor manufacturing facility in Gujarat with an investment of Rs. 3,307 crores for Wire bond Interconnect, Substrate Based Packages. The Technology would be provided by ISO Technology Sdn. Bhd. and AOI Electronics Co. Ltd. (AOI). The facility will have the capacity to produce more than 6.33 million chips per day.\n\n6.\n Vama Sundari Investments (Delhi) Private Limited (VSIPL)\nis establishing semiconductor manufacturing facility in Uttar Pradesh with an investment of Rs 3,706 crores for display driver ICs (DDIC) using Gold (Au) Bump technology along with chip probing facilities and die processing services. The Technology would be provided by Hon Hai, Taiwan. The facility will be set up as a joint venture partnership between VSIPL and Foxconn, India. The production capacity would be around 20K wafers per month/36 million chips per month.\n\n7.\n3D Glass Solutions Inc. (3DGS)\nis establishing semiconductor manufacturing facility in Odisha with an investment of Rs. 1,943 crores. The plant will handle the assembly of packaged products such as Flip Chip Ball Grid Array (FCBGA) assembly, Radio Frequency System in Package (RF SiP), Antenna in Package System in Package (AiP SiP), glass interposers with passives and silicon bridges and 3D Heterogeneous Integration (3DHI) modules. The Proposed installed capacity for glass panel substrate production, assembly and 3DHI is around 5800 panels per month, 4.20 million units per month, and 1100 units per months respectively.\n\n8.\nSiCSem Private Limited\nis establishing semiconductor manufacturing facility in Odisha with an investment of Rs. 2,066 crores. The facility will be set up in technology partnership with Clas-SiC Wafer Fab Ltd. for SiC fab and Continental Device India Pvt. Ltd. for packaging. The production capacity is 5,000 wafers/month, and the packaging capacity is 8 million units/month.\n\n9.\nContinental Device India Private Limited (CDIL)\nis expanding its semiconductor manufacturing facility in Punjab, with an investment of Rs. 117 crores. The facility will manufacture high-power discrete semiconductor devices such as MOSFETs, IGBTs, Schottky Bypass Diodes, and transistors, both in Silicon and Silicon Carbide. The production capacity will be around 158.38 million units/annum.\n\n10.\nAdvanced System in Package Technologies Private Limited (ASIP)\nis establishing semiconductor manufacturing facility in Andhra Pradesh\n,\nwith an investment of Rs. 480 crores. The facility will be set up in technology partnership with APACT Co. Ltd, South Korea. The production capacity of the facility would be around 96 million units/annum.\n\n\n\nThis information was submitted by Union Minister of State for Electronics and Information Technology Shri Jitin Prasada in Lok Sabha on 01.04.2026.\n\n\n\n****\n\nMSZ\n\n(Release ID: 2247814)\n\nVisitor Counter : 194\n\nMinistry of Electronics & IT\n\nGovernment's Semicon India Programme to develop a complete ecosystem ranging from design to manufacturing\n\nGovernment has approved 10 projects with investment commitments of about ₹1.6 lakh crore\nCommercial production from two plants has commenced; 2 more plants to start commercial production this year\n\nPosted On:\n01 APR 2026 4:59PM by PIB Delhi\n\nIndia’s electronic manufacturing strategy is driven by the Prime Minister’s vision of AtmaNirbhar Bharat and Making India a global manufacturing hub. The Government adopted a structured and targeted policy for electronics manufacturing across the entire value chain including semiconductors.\n\nAs a result of these policies, electronics manufacturing in India has expanded significantly in the last 11 years. It can be seen from the following statistics:\n\n\n\n#\n\n2014-15\n\n2024-25\n\nRemarks\n\nProduction of electronics goods (₹)\n\n~1.9 Lakh Cr\n\n~12 Lakh Cr\n\nIncreased 6 times\n\nExport of electronics goods (₹)\n\n38 thousand Cr\n\n~3.3 Lakh Cr\n\nIncreased 8 times\n\nProduction of mobile phones (₹)\n\n18 thousand Cr\n\n5.45 Lakh Cr\n\nIncreased 28 times\n\nExport of mobile phones (₹)\n\n1,500 Cr.\n\n2 Lakh Cr\n\nIncreased 127 times\n\nMobile Phone imported (units)\n\n75% of the total demand\n\n0.02% of the total demand\n\n\n\n\n\n\n\nSemicon India Programme\n\nSemiconductors is a foundational and strategic industry. Semiconductors are used in almost every device.\n\n\n\nTo promote the development of its manufacturing ecosystem in India, the Government launched Semicon India Programme in January 2022. It aims at developing a complete ecosystem, ranging from design, fabrication, assembly, testing, packaging and module manufacturing.\n\n\n\nIn a short span of four years, the Government has approved 10 projects with investment commitments of about ₹1.6 lakh crore. Commercial production from two plants (Micron and Kaynes) has commenced with 2 more plants to start commercial production this year.\n\n\n\nThe details of the approved Semiconductor manufacturing units are placed at\n Annexure I.\n\n\n\nDeveloping India’s chip design ecosystem:\n\nGovernment is developing India’s chip design ecosystem in two ways:\n\n\n\n1.\nSupporting Indian design engineers through chip design tools\n\nIn a one of its kind initiative in the world, Government has provided cutting edge chip design tools from 8 different companies to 315 universities at no cost. So far, their usage has exceeded 200 lakh hours.\n\n\n\nUsing these tools 211, chips have been taped out by 75 institutions across India including 149 chips at 180nm, SCL Mohali and 62 chip at overseas foundries.\n\n\n\n2.\nSupporting Indian design companies through grant, free design tool and fabrication support:\n\nGovernment has approved 24 projects for the design of semiconductor chips and SoCs. These projects address critical sectors such as video surveillance, drone detection, energy metering, microprocessors, satellite communications, and broadband and IoT SoCs.\n\n\n\nOut of 24 projects, 14 companies have raised venture capital funding of more than Rs 650 Cr to scale up and productize their solutions. Seven (7) chips have been successfully fabricated at various nodes including advanced nodes such as 12 nm.\n\n\n\nFurther, to enhance bilateral collaboration on opportunities to advance resilient semiconductor supply chains and leverage complementary strengths, the Government has entered into MoU with United States, Japan, European Union, Singapore and Netherlands.\n\n\n\nEmployment generation\n\nThe growth of the electronics manufacturing sector has led to substantial employment generation. As per industry estimates, it supports around 25 lakh jobs, including direct and indirect employment.\n\nOut of this, the mobile phone manufacturing sector alone supports around 12 lakh jobs, across manufacturing, logistics, supply chains and allied services.\n\n\n\nApart from this, the Government is implementing flagship schemes to further boost employment by attracting investments.\n\n\n\nUnder the India Semiconductor Mission (ISM), 10 semiconductor units are under construction. As a foundational industry, semiconductor manufacturing is expected to have a cascading impact on employment generation across the supply chain and allied sectors, leading to significant indirect job creation.\n\nSimilarly, under Electronics Component Manufacturing Scheme (ECMS), 249 applications have been received for components, base materials and capital equipments such as PCBs, capacitors, laminates etc.\n\n\n\nIndia Semiconductor Mission 2.0:\nBuilding on the success of Semicon India Programme and further enhance the capabilities in semiconductors, FM, in the Union Budget 2026-27, announced India Semiconductor Mission 2.0 for manufacture of equipment and materials, design full stack, Indian IP and fortify supply chains.\n\n\n\n****\n\n\n\nAnnexure-I\n\nDetails of approved semiconductor manufacturing projects:\n\n\n\n1.\nMicron Technology Inc.\nis establishing semiconductor manufacturing facility in Gujarat with an investment of Rs.22,516 crore. Micron’s facility in India will enable assembly and test manufacturing for both DRAM and NAND products and address demand from domestic and international markets. The production capacity is around 14 million units per week.\n\n2.\nTata Electronics Private Limited (TEPL)\nis establishing semiconductor manufacturing facility in Gujarat with an investment of Rs. 91,526 crore. The fab facility will be set up in technology partnership with PSMC, Taiwan. The production capacity of the project would be around 50,000 wafer starts per month (WSPM).\n\n3.\nTata Electronics Private Limited (TEPL)\nis establishing semiconductor manufacturing facility in Assam with an investment of Rs.27,120 crores. The facility will use indigenous semiconductor packaging technologies with a production capacity of 48 million units per day.\n\n4.\nCG Power and Industrial Solutions Limited\nis establishing semiconductor manufacturing facility in Gujarat with an investment of Rs. 7,584 crore. The facility will be set up as a joint venture partnership with Renesas Electronics America Inc., USA, and STARS Microelectronic, Thailand. The Technology would be provided for this facility by Renesas Electronics Corporation, Japan and STARS Microelectronic, Thailand. The production capacity would be around 15.07 million units per day.\n\n5.\nKaynes Technology India Limited (KTIL)\nis establishing semiconductor manufacturing facility in Gujarat with an investment of Rs. 3,307 crores for Wire bond Interconnect, Substrate Based Packages. The Technology would be provided by ISO Technology Sdn. Bhd. and AOI Electronics Co. Ltd. (AOI). The facility will have the capacity to produce more than 6.33 million chips per day.\n\n6.\n Vama Sundari Investments (Delhi) Private Limited (VSIPL)\nis establishing semiconductor manufacturing facility in Uttar Pradesh with an investment of Rs 3,706 crores for display driver ICs (DDIC) using Gold (Au) Bump technology along with chip probing facilities and die processing services. The Technology would be provided by Hon Hai, Taiwan. The facility will be set up as a joint venture partnership between VSIPL and Foxconn, India. The production capacity would be around 20K wafers per month/36 million chips per month.\n\n7.\n3D Glass Solutions Inc. (3DGS)\nis establishing semiconductor manufacturing facility in Odisha with an investment of Rs. 1,943 crores. The plant will handle the assembly of packaged products such as Flip Chip Ball Grid Array (FCBGA) assembly, Radio Frequency System in Package (RF SiP), Antenna in Package System in Package (AiP SiP), glass interposers with passives and silicon bridges and 3D Heterogeneous Integration (3DHI) modules. The Proposed installed capacity for glass panel substrate production, assembly and 3DHI is around 5800 panels per month, 4.20 million units per month, and 1100 units per months respectively.\n\n8.\nSiCSem Private Limited\nis establishing semiconductor manufacturing facility in Odisha with an investment of Rs. 2,066 crores. The facility will be set up in technology partnership with Clas-SiC Wafer Fab Ltd. for SiC fab and Continental Device India Pvt. Ltd. for packaging. The production capacity is 5,000 wafers/month, and the packaging capacity is 8 million units/month.\n\n9.\nContinental Device India Private Limited (CDIL)\nis expanding its semiconductor manufacturing facility in Punjab, with an investment of Rs. 117 crores. The facility will manufacture high-power discrete semiconductor devices such as MOSFETs, IGBTs, Schottky Bypass Diodes, and transistors, both in Silicon and Silicon Carbide. The production capacity will be around 158.38 million units/annum.\n\n10.\nAdvanced System in Package Technologies Private Limited (ASIP)\nis establishing semiconductor manufacturing facility in Andhra Pradesh\n,\nwith an investment of Rs. 480 crores. The facility will be set up in technology partnership with APACT Co. Ltd, South Korea. The production capacity of the facility would be around 96 million units/annum.\n\n\n\nThis information was submitted by Union Minister of State for Electronics and Information Technology Shri Jitin Prasada in Lok Sabha on 01.04.2026.\n\n\n\n****\n\nMSZ\n\n(Release ID: 2247814)",
  "fetched_at_utc": "2026-04-01T17:04:41.866402+00:00"
}