{
  "prid": "2247310",
  "ministry": "Ministry of Electronics & IT",
  "title": "Nyaya Setu AI Chatbot and Mascot “DISHIKA” Unveiled at DISHA Programme; BHASHINI Enables Real-Time Multilingual Translation During Vice-President’s Address",
  "posted_on_raw": "31 MAR 2026 5:11PM",
  "source_url": "https://www.pib.gov.in/PressReleasePage.aspx?PRID=2247310",
  "pdfs": [],
  "text": "Press Release Page | Press Information Bureau\n\nMinistry of Electronics & IT\n\nNyaya Setu AI Chatbot and Mascot “DISHIKA” Unveiled at DISHA Programme; BHASHINI Enables Real-Time Multilingual Translation During Vice-President’s Address\n\nPosted On:\n31 MAR 2026 5:11PM by PIB Delhi\n\nThe Nyaya Setu AI Chatbot, along with its official mascot “Dishika”, was unveiled at the DISHA programme organised by the Department of Justice at Vigyan Bhawan by the Vice-President of India, Shri C.P. Radhakrishnan, and the Minister of State (Independent Charge) for Law and Justice, Shri Arjun Ram Meghwal.\n\na\n\nNyaya Setu is a\nvoice-first, multimodal, multilingual AI-powered legal assistant\n designed to democratise access to justice by helping citizens understand legal processes, rights, and next steps through simple voice and text interactions across multiple Indian languages.\n\nBuilt and owned as a\nturnkey AI implementation by the Digital India BHASHINI Division (DIBD)\n, the platform demonstrates a complete\nend-to-end voice stack\n, enabling seamless\nvoice-led user journeys\n through integrated technologies including\nBHASHINI ASR (Automatic Speech Recognition), multilingual NLP, and conversational AI systems\n. The solution is aligned with legal guardrails and trained on frameworks such as\nBNS\n, ensuring responsible, safe, and context-aware responses.\n\nHighlighting the significance of this initiative, Shri Amitabh Nag, CEO, Digital India BHASHINI Division (DIBD), noted that Nyaya Setu represents a critical step towards making justice delivery more inclusive, where language no longer remains a barrier. Built on a\nvoice-first, end-to-end AI stack\n, the platform showcases how\nturnkey AI implementations can enable seamless voice journeys\n and bring citizen services closer to people in their own languages, advancing the broader vision of\ndemocratisation of access to justice\n.\n\nThe mascot “Dishika” acts as a friendly digital interface, guiding users through legal queries and enhancing accessibility, trust, and engagement, especially for first-time users navigating the justice system.\n\nDuring the programme, BHASHINI’s\nShrutlekh system\n enabled\nreal-time transcription and multilingual translation\n of the Hon’ble Vice-President’s address and other sessions, ensuring seamless accessibility and wider audience participation.\n\nNyaya Setu stands as a strong example of how voice-driven, AI-enabled platforms can advance the democratisation of access to justice by simplifying legal processes for citizens, particularly those facing linguistic and procedural barriers. The solution further reinforces BHASHINI’s role in enabling scalable, inclusive, and voice-enabled digital public infrastructure that brings justice closer to every citizen.\n\nBHASHINI is India’s AI-powered language technology initiative under the Ministry of Electronics and Information Technology (MeitY), implemented by the Digital India BHASHINI Division (DIBD), an Independent Business Division under Digital India Corporation, a Section 8 company under MeitY. It has developed one of the world’s largest AI inferencing platforms, the National Hub for Language Technology (NHLT), enabling multilingual AI capabilities across Indian and international languages through advanced speech and text technologies. BHASHINI manages a robust ecosystem powering open source models from academic institutions and organisations, supports more than 500 government websites, and processes over 15 million inferences daily. The platform offers over 20 specialised NLP services across 36 text and 23 voice languages, including support for complex tribal dialects and multiple international languages.\n\nThe current Nyaya Setu implementation has been developed by DIBD as a turnkey solution to demonstrate the end-to-end capabilities of language AI through a seamless, voice-led user journey.\n\n\n\n****\n\nMSZ\n\n(Release ID: 2247310)\n\nVisitor Counter : 199\n\nMinistry of Electronics & IT\n\nNyaya Setu AI Chatbot and Mascot “DISHIKA” Unveiled at DISHA Programme; BHASHINI Enables Real-Time Multilingual Translation During Vice-President’s Address\n\nPosted On:\n31 MAR 2026 5:11PM by PIB Delhi\n\nThe Nyaya Setu AI Chatbot, along with its official mascot “Dishika”, was unveiled at the DISHA programme organised by the Department of Justice at Vigyan Bhawan by the Vice-President of India, Shri C.P. Radhakrishnan, and the Minister of State (Independent Charge) for Law and Justice, Shri Arjun Ram Meghwal.\n\na\n\nNyaya Setu is a\nvoice-first, multimodal, multilingual AI-powered legal assistant\n designed to democratise access to justice by helping citizens understand legal processes, rights, and next steps through simple voice and text interactions across multiple Indian languages.\n\nBuilt and owned as a\nturnkey AI implementation by the Digital India BHASHINI Division (DIBD)\n, the platform demonstrates a complete\nend-to-end voice stack\n, enabling seamless\nvoice-led user journeys\n through integrated technologies including\nBHASHINI ASR (Automatic Speech Recognition), multilingual NLP, and conversational AI systems\n. The solution is aligned with legal guardrails and trained on frameworks such as\nBNS\n, ensuring responsible, safe, and context-aware responses.\n\nHighlighting the significance of this initiative, Shri Amitabh Nag, CEO, Digital India BHASHINI Division (DIBD), noted that Nyaya Setu represents a critical step towards making justice delivery more inclusive, where language no longer remains a barrier. Built on a\nvoice-first, end-to-end AI stack\n, the platform showcases how\nturnkey AI implementations can enable seamless voice journeys\n and bring citizen services closer to people in their own languages, advancing the broader vision of\ndemocratisation of access to justice\n.\n\nThe mascot “Dishika” acts as a friendly digital interface, guiding users through legal queries and enhancing accessibility, trust, and engagement, especially for first-time users navigating the justice system.\n\nDuring the programme, BHASHINI’s\nShrutlekh system\n enabled\nreal-time transcription and multilingual translation\n of the Hon’ble Vice-President’s address and other sessions, ensuring seamless accessibility and wider audience participation.\n\nNyaya Setu stands as a strong example of how voice-driven, AI-enabled platforms can advance the democratisation of access to justice by simplifying legal processes for citizens, particularly those facing linguistic and procedural barriers. The solution further reinforces BHASHINI’s role in enabling scalable, inclusive, and voice-enabled digital public infrastructure that brings justice closer to every citizen.\n\nBHASHINI is India’s AI-powered language technology initiative under the Ministry of Electronics and Information Technology (MeitY), implemented by the Digital India BHASHINI Division (DIBD), an Independent Business Division under Digital India Corporation, a Section 8 company under MeitY. It has developed one of the world’s largest AI inferencing platforms, the National Hub for Language Technology (NHLT), enabling multilingual AI capabilities across Indian and international languages through advanced speech and text technologies. BHASHINI manages a robust ecosystem powering open source models from academic institutions and organisations, supports more than 500 government websites, and processes over 15 million inferences daily. The platform offers over 20 specialised NLP services across 36 text and 23 voice languages, including support for complex tribal dialects and multiple international languages.\n\nThe current Nyaya Setu implementation has been developed by DIBD as a turnkey solution to demonstrate the end-to-end capabilities of language AI through a seamless, voice-led user journey.\n\n\n\n****\n\nMSZ\n\n(Release ID: 2247310)",
  "fetched_at_utc": "2026-03-31T15:10:17.744499+00:00"
}