{
  "prid": "2248572",
  "ministry": "Ministry of Electronics & IT",
  "title": "IndiaAI and CDSCO Launch Health Innovation Acceleration Hackathon",
  "posted_on_raw": "02 APR 2026 6:59PM",
  "source_url": "https://www.pib.gov.in/PressReleasePage.aspx?PRID=2248572",
  "pdfs": [],
  "text": "Press Release Page | Press Information Bureau\n\nMinistry of Electronics & IT\n\nIndiaAI and CDSCO Launch Health Innovation Acceleration Hackathon\n\nApplications Open till April 17, 2026\nStartups and companies are invited to develop regulatory workflow automation and privacy-preserving solutions\n\nPosted On:\n02 APR 2026 6:59PM by PIB Delhi\n\nIndiaAI, an Independent Business Division (IBD) under the Digital India Corporation (DIC) of the Ministry of Electronics and IT (MeitY), announced the launch of CDSCO-IndiaAI Health Innovation Acceleration Hackathon on April 2, 2026, in collaboration with the Central Drugs Standard Control Organisation (CDSCO). This initiative falls under the IndiaAI Application Development Initiative (IADI), aimed at promoting the development and adoption of AI applications in critical sectors. The hackathon invites participants to build a comprehensive, end-to-end AI solution across two stages to streamline regulatory workflows.\n\nIn Stage 1, applicants will be expected to develop a robust data anonymisation tool. Additionally, the solution must feature intelligent document summarisation to extract and standardise critical data from SUGAM applications, Serious Adverse Event (SAE) narratives, and meeting transcripts. Furthermore, the system should be able to perform tasks like assessments and flagging of missing fields in regulatory forms, classify cases by severity, highlight substantive changes between document versions and automatically generate formal inspection reports from unstructured, handwritten notes.\n\nUnder Stage 2, shortlisted teams must refine their models using proprietary CDSCO datasets and enable integration with the SUGAM and MD Online portals to measurably accelerate regulatory approvals and enhance access to healthcare innovations, concluding with a detailed project report on the outcomes.\n\nPrizes and Incentives:\n\nThe hackathon features a multi-stage evaluation process. The top 10 teams from Stage 1 will advance to an exclusive 5-day on-premises development round at the CDSCO office in New Delhi\n\nThe winning team will receive up to ₹10 Lakh along with an opportunity to secure a one-year work contract worth up to ₹50 Lakh to develop, integrate and deploy the solution\n\nOther awards include up to ₹7 Lakh for the second prize and up to ₹3 Lakh for the third prize. Additionally, a special prize of up to ₹5 Lakh will be awarded to an all-women team\n\nInterested participants can apply via the AIKosh portal (\nhttps://aikosh.indiaai.gov.in/home\n).\n\nSubmissions are open till April 17, 2026\n\n****\n\nMSZ\n\n(Release ID: 2248572)\n\nVisitor Counter : 14\n\nMinistry of Electronics & IT\n\nIndiaAI and CDSCO Launch Health Innovation Acceleration Hackathon\n\nApplications Open till April 17, 2026\nStartups and companies are invited to develop regulatory workflow automation and privacy-preserving solutions\n\nPosted On:\n02 APR 2026 6:59PM by PIB Delhi\n\nIndiaAI, an Independent Business Division (IBD) under the Digital India Corporation (DIC) of the Ministry of Electronics and IT (MeitY), announced the launch of CDSCO-IndiaAI Health Innovation Acceleration Hackathon on April 2, 2026, in collaboration with the Central Drugs Standard Control Organisation (CDSCO). This initiative falls under the IndiaAI Application Development Initiative (IADI), aimed at promoting the development and adoption of AI applications in critical sectors. The hackathon invites participants to build a comprehensive, end-to-end AI solution across two stages to streamline regulatory workflows.\n\nIn Stage 1, applicants will be expected to develop a robust data anonymisation tool. Additionally, the solution must feature intelligent document summarisation to extract and standardise critical data from SUGAM applications, Serious Adverse Event (SAE) narratives, and meeting transcripts. Furthermore, the system should be able to perform tasks like assessments and flagging of missing fields in regulatory forms, classify cases by severity, highlight substantive changes between document versions and automatically generate formal inspection reports from unstructured, handwritten notes.\n\nUnder Stage 2, shortlisted teams must refine their models using proprietary CDSCO datasets and enable integration with the SUGAM and MD Online portals to measurably accelerate regulatory approvals and enhance access to healthcare innovations, concluding with a detailed project report on the outcomes.\n\nPrizes and Incentives:\n\nThe hackathon features a multi-stage evaluation process. The top 10 teams from Stage 1 will advance to an exclusive 5-day on-premises development round at the CDSCO office in New Delhi\n\nThe winning team will receive up to ₹10 Lakh along with an opportunity to secure a one-year work contract worth up to ₹50 Lakh to develop, integrate and deploy the solution\n\nOther awards include up to ₹7 Lakh for the second prize and up to ₹3 Lakh for the third prize. Additionally, a special prize of up to ₹5 Lakh will be awarded to an all-women team\n\nInterested participants can apply via the AIKosh portal (\nhttps://aikosh.indiaai.gov.in/home\n).\n\nSubmissions are open till April 17, 2026\n\n****\n\nMSZ\n\n(Release ID: 2248572)",
  "fetched_at_utc": "2026-04-02T13:42:18.459268+00:00"
}